CHANGELOG.md
README.md
RELEASE.md
pyproject.toml
tsconfig.json
yarn.lock
examples/demo_jupyterlab_run_and_reload.gif
jupyterlab_run_and_reload/_version.py
jupyterlab_run_and_reload-4.0.0.data/data/share/jupyter/labextensions/jupyterlab_run_and_reload/package.json
jupyterlab_run_and_reload-4.0.0.data/data/share/jupyter/labextensions/jupyterlab_run_and_reload/schemas/jupyterlab_run_and_reload/package.json.orig
jupyterlab_run_and_reload-4.0.0.data/data/share/jupyter/labextensions/jupyterlab_run_and_reload/schemas/jupyterlab_run_and_reload/plugin.json
jupyterlab_run_and_reload-4.0.0.data/data/share/jupyter/labextensions/jupyterlab_run_and_reload/static/50.4c028b7b59c1a618c04c.js
jupyterlab_run_and_reload-4.0.0.data/data/share/jupyter/labextensions/jupyterlab_run_and_reload/static/728.949edf23eed0d59e0111.js
jupyterlab_run_and_reload-4.0.0.data/data/share/jupyter/labextensions/jupyterlab_run_and_reload/static/remoteEntry.e56288bb93ab506fc145.js
jupyterlab_run_and_reload-4.0.0.data/data/share/jupyter/labextensions/jupyterlab_run_and_reload/static/style.js
jupyterlab_run_and_reload-4.0.0.data/data/share/jupyter/labextensions/jupyterlab_run_and_reload/static/third-party-licenses.json
jupyterlab_run_and_reload-4.0.0.data/data/share/jupyter/labextensions/jupyterlab_run_and_reload/install.json
jupyterlab_run_and_reload-4.0.0.dist-info/METADATA
jupyterlab_run_and_reload-4.0.0.dist-info/WHEEL
jupyterlab_run_and_reload-4.0.0.dist-info/licenses/LICENSE
jupyterlab_run_and_reload-4.0.0.dist-info/RECORD
