Metadata-Version: 2.4
Name: jupyterlab_run_and_reload
Version: 4.0.0
Summary: A JupyterLab extension to run all notebook cells and reload static content (e.g. PDF).
Project-URL: Homepage, https://github.com/imcovangent/jupyterlab_run_and_reload
Project-URL: Bug Tracker, https://github.com/imcovangent/jupyterlab_run_and_reload/issues
Project-URL: Repository, https://github.com/imcovangent/jupyterlab_run_and_reload.git
Author-email: Imco van Gent <imcovangent@gmail.com>
License: BSD 3-Clause License
License-File: LICENSE
Keywords: jupyter,jupyterlab,jupyterlab-extension
Classifier: Framework :: Jupyter
Classifier: Framework :: Jupyter :: JupyterLab
Classifier: Framework :: Jupyter :: JupyterLab :: 4
Classifier: Framework :: Jupyter :: JupyterLab :: Extensions
Classifier: Framework :: Jupyter :: JupyterLab :: Extensions :: Prebuilt
Classifier: License :: OSI Approved :: BSD License
Classifier: Programming Language :: Python
Classifier: Programming Language :: Python :: 3
Classifier: Programming Language :: Python :: 3.9
Classifier: Programming Language :: Python :: 3.10
Classifier: Programming Language :: Python :: 3.11
Classifier: Programming Language :: Python :: 3.12
Classifier: Programming Language :: Python :: 3.13
Requires-Python: >=3.9
